{
  "slug": "retention",
  "short_name": "留存",
  "seo": {
    "title": "留存與同群分析",
    "description": "使用者留存分析與同群分析，幫你看出誰會回來。立即掌握產品黏著度——不靠抽樣，不用猜測。建立在你的事件之上。",
    "keywords": [
      "使用者留存分析",
      "同群分析"
    ]
  },
  "hero": {
    "heading": "留存：誰會回來？",
    "subheading": "查看使用者在註冊、啟用或任何關鍵動作之後是否會回訪。以同群為基礎的留存，呈現真實黏著度，而不是虛榮指標。",
    "badges": [
      "以同群為基礎的留存",
      "任何起始與回訪事件",
      "不抽樣",
      "比較區隔"
    ]
  },
  "definition": {
    "title": "留存的意思",
    "text": "**留存**指的是使用者做過一次某件事之後，會再回來的比例。它回答的是：*在某一週做了 X 的人之中，有多少人在之後做了 Y？*\n\n就是這樣。沒有會話門檻，也沒有任意的「活躍」定義，只有一個清楚的畫面：誰會留下，誰不會。\n\n流量和註冊數字看起來可能很漂亮，但產品卻不一定留得住人。留存能告訴你那些數字無法回答的事：\n\n- **你的產品是否會讓人養成習慣** - 使用者第一次用完之後會再回來嗎？\n- **流失何時發生** - 他們是在第 1 天、第 1 週，還是第 1 個月離開？\n- **哪些區隔會留下來** - 某些同群（例如依方案、來源或功能）是否有更好的留存？\n\n在 OpenPanel 中，留存建立在你的 **事件** 上。你可以選擇一個初始事件（例如 `signup_completed`、`first_purchase`）和一個回訪事件（例如 `feature_used`、`session_started`）。OpenPanel 會依使用者完成初始事件的時間將他們分成不同同群，並顯示他們在後續期間做出回訪事件的百分比。不需要額外埋點——同樣驅動漏斗與使用者檔案的事件，也驅動了留存。"
  },
  "capabilities_section": {
    "title": "你可以用留存做什麼",
    "intro": "從每週同群到區隔比較，留存提供你產品黏著度的訊號。"
  },
  "capabilities": [
    {
      "title": "以同群為基礎的留存",
      "description": "依使用者完成初始事件的時間分組（例如註冊週）。查看他們在第 1 週、第 2 週、第 3 週以及之後的回訪比例。"
    },
    {
      "title": "任何起始與回訪事件",
      "description": "用你自己的方式定義留存：註冊 → 登入、首次購買 → 再次購買、feature_used → 再次 feature_used。沒有固定定義。"
    },
    {
      "title": "一眼讀懂格狀圖",
      "description": "留存格狀圖會把同群放在列、時間區間放在欄。數字越高 = 黏著度越高；流失模式則能看出該把重點放在哪裡。"
    },
    {
      "title": "比較區隔",
      "description": "可依方案、來源或自訂屬性進行篩選或分群。找出哪些同群留存更好，以及原因。"
    },
    {
      "title": "不抽樣",
      "description": "留存是根據每一筆事件計算的。不抽樣、不估算——你看到的是實際黏著度。"
    },
    {
      "title": "儀表板與分享",
      "description": "把留存圖表加入儀表板，與漏斗和其他報表並列。可分享給 PM 和創辦人。"
    }
  ],
  "screenshots": [
    {
      "src": "/features/feature-retention.webp",
      "alt": "顯示隨時間黏著度的留存同群格狀圖",
      "caption": "一眼看懂同群留存。列 = 同群，欄 = 時間區間。看出誰會回來。"
    },
    {
      "src": "/features/feature-retention.webp",
      "alt": "為留存選擇初始與回訪事件",
      "caption": "選擇定義你的產品留存的起始與回訪事件。"
    }
  ],
  "how_it_works": {
    "title": "如何閱讀留存圖",
    "intro": "一旦知道重點看什麼，留存圖其實很簡單。",
    "steps": [
      {
        "title": "選擇你的初始與回訪事件",
        "description": "初始事件定義同群（例如 signup_completed）。回訪事件定義「回來了」（例如 session_started 或 feature_used）。在某一期間做出初始事件的每位使用者，就是一個同群。"
      },
      {
        "title": "閱讀格狀圖",
        "description": "列是同群（例如「1 月 6 日當週」）。欄是初始事件之後的時間區間（例如第 1 週、第 2 週）。每個儲存格代表該同群在那個期間做出回訪事件的百分比。數字越高 = 黏著度越高。"
      },
      {
        "title": "找出模式",
        "description": "找出留存好的同群，以及快速流失的同群。比較區隔（例如依方案或來源）來看哪些使用者會留下，並據此排定產品與成長工作的優先順序。"
      }
    ]
  },
  "use_cases": {
    "title": "團隊如何使用留存",
    "intro": "PM 和創辦人會用留存來分辨訊號與雜訊。",
    "items": [
      {
        "title": "產品經理",
        "description": "看出哪些功能與流程會帶來重複使用。優先投入能提升留存的工作，而不只是提高註冊數。比較同群，了解哪些差異會讓使用者留下來或流失。"
      },
      {
        "title": "創辦人",
        "description": "留存是產品市場契合度的真相。一個數字——例如第 2 週或第 4 週留存——往往比整體成長更能說明問題。可用於董事會更新與策略討論。"
      },
      {
        "title": "成長與分析",
        "description": "衡量導入流程或啟用變更對留存的影響。依獲客來源或方案分群，把資源投資在留存最佳的管道與區隔。"
      }
    ]
  },
  "related_features": [
    {
      "slug": "event-tracking",
      "title": "事件追蹤",
      "description": "留存建立在事件之上。先追蹤註冊、會話和功能使用。"
    },
    {
      "slug": "funnels",
      "title": "漏斗",
      "description": "看出使用者在無法留存之前是在哪裡流失。漏斗與留存相輔相成。"
    }
  ],
  "faqs": {
    "title": "常見問題",
    "intro": "關於 OpenPanel 留存分析的常見問題。",
    "items": [
      {
        "question": "留存分析和漏斗分析有什麼不同？",
        "answer": "漏斗回答的是「使用者在一個流程中是在哪裡流失？」留存回答的是「在做了 X 的使用者之中，有多少人回來做 Y？」兩者使用相同的事件；留存著重於隨時間重複發生的行為，漏斗則著重於一次性的流程。"
      },
      {
        "question": "留存可以使用任何事件嗎？",
        "answer": "可以。你可以選擇一個初始事件（例如 signup_completed、first_purchase）和一個回訪事件（例如 session_started、feature_used）。OpenPanel 會依使用者完成初始事件的時間將他們分群，並顯示他們在後續期間做出回訪事件的百分比。"
      },
      {
        "question": "我要怎麼知道我的留存表現好不好？",
        "answer": "沒有通用的基準；這取決於你的產品與同群。重點是趨勢與區隔比較：是否持續改善，以及哪些同群留存更好。留存會提供你數據；至於什麼叫做「好」，則由你根據產品來判斷。"
      }
    ]
  },
  "cta": {
    "label": "幾分鐘內看見你的留存",
    "href": "https://dashboard.openpanel.dev/onboarding"
  }
}
